BFCPU.v
 module main;
    wire [15:0] PC;
    wire [3:0] INST;
    wire [14:0] DP;
    wire [7:0] WDATA;
    wire [7:0] RDATA;  
    wire RF;
    wire WF;
    reg clk = 0;
    
    //Instruction decode
    wire SGN = INST[0]; 
    wire INP = INST[3:0]==4'b0101; 
    wire OUTP = INST[3:0]==4'b0100; 
    wire DOP = INST[3:1]==3'b001; 
    wire DPOP = INST[3:1]==3'b000;  
    wire RD = INST[3:0]==4'b1100;
    wire WD = INST[3:0]==4'b1101;
    wire LD = INST[3:0]==4'b1011;

    
    OPC OPC1(IZ,PC,RF,WF,INST,clk);
    DPC DPC1(DPOP,SGN,clk,DP);
    DC DC1(DOP,INP,OUTP,SGN,RDATA,WDATA,LD,IZ,clk);
    DMEMC DMEMC1(RD,WD,WDATA,DP,RF,WF,RDATA,clk);

    initial begin
        $dumpfile("outp/my_dumpfile.vcd"); 
        $dumpvars(0,main);
        //#200 $finish;
    end

    always #1 clk = !clk;

    always @(posedge clk)
    begin 
        //$display(" INST %b DP %d WDATA %0d PC=%d",INST,DP,WDATA,PC);
    
        //$display(PC);
        //check if last inst from mem is fetched
        if((^INST === 1'bx)) begin
            
            $display("\ntime is %d",$time);
            $finish;
        end
    end
endmodule




module OPC(IZ,PC,RF,WF,INST,clk);
    input clk;
    input IZ,RF,WF;
    output reg [15:0] PC;
    output reg [3:0] INST;
    
    
    reg [7:0] bracketcount;
    reg [2:0] IMEM [65536-1:0];
    reg [2:0] NEXTOP;  //next true inst from program
    reg [3:0] NEXTSTATE; //next state

    //decoding of current inst
    parameter 
    INP     =4'b0101,
    OUTP    =4'b0100,
    DI      =4'b0010,
    DD      =4'b0011,
    DPI     =4'b0000,
    DPD     =4'b0001,
    BZ      =4'b0110,
    BNZ     =4'b0111,
    RD      =4'b1100,
    WD      =4'b1101,
    LD      =4'b1011,
    WIP     =4'b1001,
    RIP     =4'b1000,
    SF      =4'b1110,
    SB      =4'b1111,
    NOP     =4'b1010;
    
    parameter
    NINP    =3'b101,
    NOUTP   =3'b100,
    NDI     =4'b010,
    NDD     =4'b011,
    NDPI    =4'b000,
    NDPD    =4'b001,
    NBZ     =4'b110,
    NBNZ     =4'b111;
    
    
    integer PCDELTA = 0;
    integer bracketdelta = 0;
    
    initial begin
        $readmemb("storage_files/program.bin", IMEM);
        PC = 1;
        NEXTOP = IMEM[1];
        INST = { 1'b0,IMEM[0]};
    end
    
    
    
    
    
    always @(NEXTOP,INST,IZ,RF,WF,clk) begin
        case (INST)
            INP:begin
                    case(NEXTOP)
                        NDPI:begin 
                                NEXTSTATE = WD;
                                PCDELTA = 0;
                                end
                        NDPD: begin 
                                NEXTSTATE = WD;
                                PCDELTA = 0;
                                end
                        BZ: begin
                                NEXTSTATE = WD;
                                PCDELTA = 0;
                                end
                        BNZ: begin
                                NEXTSTATE = WD;
                                PCDELTA = 0;
                                end
                        default:begin 
                                NEXTSTATE = { 1'b0,NEXTOP};
                                PCDELTA = 1;
                                end
                    endcase
                end
            OUTP:begin
                    case(NEXTOP)
                        NDPI:begin 
                                NEXTSTATE = WD;
                                PCDELTA = 0;
                                end
                        NDPD: begin 
                                NEXTSTATE = WD;
                                PCDELTA = 0;
                                end
                        BZ: begin
                                NEXTSTATE = WD;
                                PCDELTA = 0;
                                end
                        BNZ: begin
                                NEXTSTATE = WD;
                                PCDELTA = 0;
                                end
                        default:begin 
                                NEXTSTATE = { 1'b0,NEXTOP};
                                PCDELTA = 1;
                                end
                    endcase
                end 
            DI:begin
                    case(NEXTOP)
                        NDPI:begin 
                            NEXTSTATE = WD;
                            PCDELTA = 0;
                            end
                        NDPD:begin 
                            NEXTSTATE = WD;
                            PCDELTA = 0;
                            end
                        BZ: begin
                                NEXTSTATE = WD;
                                PCDELTA = 0;
                                end
                        BNZ: begin
                                NEXTSTATE = WD;
                                PCDELTA = 0;
                                end
                        default:begin 
                            NEXTSTATE = { 1'b0,NEXTOP};
                            PCDELTA = 1;
                            end
                    endcase
                end 
            DD:begin
                    case(NEXTOP)
                        NDPI:begin 
                            NEXTSTATE = WD;
                            PCDELTA = 0;
                            end
                        NDPD:begin 
                            NEXTSTATE = WD;
                            PCDELTA = 0;
                            end
                        BZ: begin
                                NEXTSTATE = WD;
                                PCDELTA = 0;
                                end
                        BNZ: begin
                                NEXTSTATE = WD;
                                PCDELTA = 0;
                                end
                        default:begin 
                            NEXTSTATE = { 1'b0,NEXTOP};
                            PCDELTA = 1;
                            end
                    endcase
                end 
            DPI:begin
                    case(NEXTOP)
                        NDPI:begin 
                                NEXTSTATE = { 1'b0,NEXTOP};
                                PCDELTA = 1;
                            end
                        NDPD:begin 
                                NEXTSTATE = { 1'b0,NEXTOP};
                                PCDELTA = 1;
                            end
                        NINP:begin 
                                NEXTSTATE = { 1'b0,NEXTOP};
                                PCDELTA = 1;
                            end
                        default:begin 
                                NEXTSTATE = RD;
                                PCDELTA = 0;
                            end
                    endcase
                end
            DPD:begin
                    case(NEXTOP)
                        NDPI:begin 
                                NEXTSTATE = { 1'b0,NEXTOP};
                                PCDELTA = 1;
                            end
                        NDPD:begin 
                                NEXTSTATE = { 1'b0,NEXTOP};
                                PCDELTA = 1;
                            end
                        NINP:begin 
                                NEXTSTATE = { 1'b0,NEXTOP};
                                PCDELTA = 1;
                            end
                        default:begin 
                                NEXTSTATE = RD;
                                PCDELTA = 0;
                            end
                    endcase
                end
            RD:begin
                    //$display("reading");
                    NEXTSTATE = RIP;
                    PCDELTA = 0;
                end
            WD:begin
                    //$display("writing");
                    NEXTSTATE = WIP;
                    PCDELTA = 0;
                end
            LD:begin
                    //$display("Read finished");
                    NEXTSTATE = { 1'b0,NEXTOP};
                    PCDELTA = 1;
                end
            WIP:begin
                    if(WF) begin
                        //$display("Write finished");
                        NEXTSTATE = { 1'b0,NEXTOP};
                        PCDELTA = 1;
                    end
                    else begin
                        NEXTSTATE = WIP;
                        PCDELTA = 0;
                    end
                end
            RIP:begin
                    if(RF) begin
                        //$display("Read finished");
                        NEXTSTATE = LD;
                        PCDELTA = 0;
                    end
                    else begin
                        NEXTSTATE = RIP;
                        PCDELTA = 0;
                    end
                end
            BZ:begin
                    if(IZ) begin
                        NEXTSTATE = SF;
                        bracketcount=0;
                        PCDELTA = 0;
                    end
                    else begin
                        NEXTSTATE = { 1'b0,NEXTOP};
                        PCDELTA = 1;
                    end
                end
            BNZ:begin
                    if(!IZ) begin
                        bracketcount =0;
                        NEXTSTATE = SB;
                        PCDELTA = -2;
                    end
                    else begin
                        NEXTSTATE = { 1'b0,NEXTOP};
                        PCDELTA = 1;
                    end
                end
            SF:begin
                    //$display("NEXTOP =%b PC=%d",NEXTOP,PC);
                    if( NEXTOP == BNZ && bracketcount==0) begin
                        //$display("found");
                        NEXTSTATE = NOP;
                        PCDELTA = 1;
                    end else begin
                        if(NEXTOP == BZ)
                            bracketdelta = 1;
                        if(NEXTOP == BNZ)
                            bracketdelta = -1;    
                        NEXTSTATE = SF;
                        PCDELTA = 1;
                    end
                end
            SB:begin
                    if(NEXTOP == BZ && bracketcount==0) begin
                        PCDELTA = 1;
                        NEXTSTATE = NOP;
                    end
                    else begin
                        //$display("NEXTOP =%b PC=%d",NEXTOP,PC);
                        if(NEXTOP == BNZ)
                            bracketdelta = 1;
                        if(NEXTOP == BZ)
                            bracketdelta = -1;   
                        NEXTSTATE = SB;
                        PCDELTA = -1;
                    end
                end
            NOP:begin
                    NEXTSTATE = { 1'b0,NEXTOP};
                    PCDELTA = 1;
                    
                end
            default: begin
                        //$display(INST);
                        //$display("something went wrong");
                        //$finish;
                        NEXTOP = NOP;
                    end
        endcase
            
    
    end
    
    
    always @(posedge clk) begin
        
        PC <= PC + PCDELTA;
        INST <= NEXTSTATE;
        if(PCDELTA != 0) begin
            NEXTOP <= IMEM[PC+PCDELTA];
        end
        
        if(bracketdelta !=0) begin
            bracketcount <=bracketcount+ bracketdelta;
            bracketdelta <=0;
        end
        
        //$display("bracketcount",bracketcount);
        /*if(NEXTSTATE == WD)
            $display("Writing)");
        if(NEXTSTATE == RD)
            $display("Reading");
        */
    end
endmodule

module DPC(DPOP,SGN,clk,DP);
    input DPOP, SGN,clk;
    output reg [14:0] DP;
    
    initial begin
        DP <= 0;
    end
    
    always @(posedge clk) 
    begin
        if(DPOP)
            DP <= (SGN) ? DP - 1: DP+1;
    end
endmodule

module DC(DOP,INP,OUTP,SGN,RDATA,WDATA,LD,IZ,clk);
    input DOP,OUTP,INP,SGN,LD,clk;
    input [7:0] RDATA;
    output reg [7:0] WDATA;
    output wire IZ;
    
    integer COUNT = 0;
    
    
    integer INPMEM;
    integer OUTC;
    integer OUTD;
    assign IZ = WDATA == 0;
    
    initial begin
        INPMEM = $fopen("storage_files/programinput" ,"r");
        WDATA = 0;
    end
    
    always @(posedge clk) begin
        
        if(DOP)
            WDATA <= (SGN) ? WDATA-1 : WDATA +1;
        else if(INP)
            WDATA <= $fgetc(INPMEM);
        else if(LD)
            WDATA <= RDATA;
        else if(OUTP) begin
            //$fwrite(OUTC,"%c",WDATA);
            //$fwrite(OUTD,"%d",WDATA);
            //$display("%c",WDATA);
            $write("%c", WDATA);
            
        end
    end
    
    
    
endmodule

 module DMEMC(RD,WD,WDATA,DP,RF,WF,RDATA,clk);
    input RD,WD,clk;
    input [14:0] DP;
    input [7:0] WDATA;
    output reg RF,WF;
    output reg [7:0] RDATA;
    
    reg [7:0] DMEM[2**15-1:0];
    
    initial begin
        $readmemh("storage_files/DMEM.txt", DMEM);
        RF <=0;
        WF <=0;
    end
    always @(posedge RD) begin
        RDATA <= #2 DMEM[DP];
        RF <= #4 1;
        RF <= #6 0;
    end
    
    always @(posedge WD) begin
        DMEM[DP] <= #2 WDATA;
        WF <= #4 1;
        WF <= #6 0;
    end
endmodule

outp/my_dumpfile.vcd
$date
	Wed Sep 19 13:52:35 2018
$end
$version
	Icarus Verilog
$end
$timescale
	1s
$end
$scope module main $end
$var wire 1 ! WF $end
$var wire 8 " WDATA [7:0] $end
$var wire 1 # WD $end
$var wire 1 $ SGN $end
$var wire 1 % RF $end
$var wire 8 & RDATA [7:0] $end
$var wire 1 ' RD $end
$var wire 16 ( PC [15:0] $end
$var wire 1 ) OUTP $end
$var wire 1 * LD $end
$var wire 1 + IZ $end
$var wire 4 , INST [3:0] $end
$var wire 1 - INP $end
$var wire 1 . DPOP $end
$var wire 15 / DP [14:0] $end
$var wire 1 0 DOP $end
$var reg 1 1 clk $end
$scope module DC1 $end
$var wire 1 0 DOP $end
$var wire 1 - INP $end
$var wire 1 * LD $end
$var wire 1 ) OUTP $end
$var wire 1 $ SGN $end
$var wire 1 1 clk $end
$var wire 8 2 RDATA [7:0] $end
$var wire 1 + IZ $end
$var reg 8 3 WDATA [7:0] $end
$var integer 32 4 COUNT [31:0] $end
$var integer 32 5 INPMEM [31:0] $end
$upscope $end
$scope module DMEMC1 $end
$var wire 1 ' RD $end
$var wire 1 # WD $end
$var wire 8 6 WDATA [7:0] $end
$var wire 1 1 clk $end
$var wire 15 7 DP [14:0] $end
$var reg 8 8 RDATA [7:0] $end
$var reg 1 % RF $end
$var reg 1 ! WF $end
$upscope $end
$scope module DPC1 $end
$var wire 1 . DPOP $end
$var wire 1 $ SGN $end
$var wire 1 1 clk $end
$var reg 15 9 DP [14:0] $end
$upscope $end
$scope module OPC1 $end
$var wire 1 + IZ $end
$var wire 1 % RF $end
$var wire 1 ! WF $end
$var wire 1 1 clk $end
$var reg 4 : INST [3:0] $end
$var reg 3 ; NEXTOP [2:0] $end
$var reg 4 < NEXTSTATE [3:0] $end
$var reg 16 = PC [15:0] $end
$var reg 8 > bracketcount [7:0] $end
$var integer 32 ? PCDELTA [31:0] $end
$var integer 32 @ bracketdelta [31:0] $end
$upscope $end
$upscope $end
$enddefinitions $end
#0
$dumpvars
b0 @
b0 ?
bx >
b1 =
b1101 <
b110 ;
b10 :
b0 9
bx 8
b0 7
b0 6
b10000000000000000000000000000011 5
b0 4
b0 3
bx 2
01
10
b0 /
0.
0-
b10 ,
1+
0*
0)
b1 (
0'
bx &
0%
0$
0#
b0 "
0!
$end
#1
00
1$
b1001 <
1#
b1101 ,
b1101 :
0+
b1 "
b1 3
b1 6
11
#2
01
#3
0#
b1001 ,
b1001 :
11
#4
01
#5
b1 ?
b110 <
1!
11
#6
01
#7
0$
b11 <
b11 ;
b110 ,
b110 :
b10 (
b10 =
0!
11
#8
01
#9
b0 ?
b1101 <
10
1$
b110 ;
b11 ,
b11 :
b11 (
b11 =
11
#10
01
#11
b1001 <
00
1+
b0 "
b0 3
b0 6
1#
b1101 ,
b1101 :
11
#12
01
#13
0#
b1001 ,
b1001 :
11
#14
01
#15
b1 ?
b110 <
1!
11
#16
01
#17
0$
b0 ?
b0 >
b1110 <
b1 ;
b110 ,
b110 :
b100 (
b100 =
0!
11
#18
01
#19
b1 ?
b1110 ,
b1110 :
11
#20
01
#21
b101 (
b101 =
11
#22
01
#23
b1 @
b110 ;
b110 (
b110 =
11
#24
01
#25
b0 @
b1 >
b10 ;
b111 (
b111 =
11
#26
01
#27
b1 @
b110 ;
b1000 (
b1000 =
11
#28
01
#29
b0 @
b10 >
b11 ;
b1001 (
b1001 =
11
#30
01
#31
b1010 (
b1010 =
11
#32
01
#33
b1011 (
b1011 =
11
#34
01
#35
b0 ;
b1100 (
b1100 =
11
#36
01
#37
b11111111111111111111111111111111 @
b111 ;
b1101 (
b1101 =
11
#38
01
#39
b0 @
b1 >
b11 ;
b1110 (
b1110 =
11
#40
01
#41
b1 @
b110 ;
b1111 (
b1111 =
11
#42
01
#43
b0 @
b10 >
b1 ;
b10000 (
b10000 =
11
#44
01
#45
b10001 (
b10001 =
11
#46
01
#47
b10010 (
b10010 =
11
#48
01
#49
b11111111111111111111111111111111 @
b111 ;
b10011 (
b10011 =
11
#50
01
#51
b0 @
b1 >
b10100 (
b10100 =
11
#52
b11111111111111111111111111111111 @
01
#53
b0 @
b0 >
b10101 (
b10101 =
11
#54
b1010 <
01
#55
b0 <
b0 ;
b1010 ,
b1010 :
b10110 (
b10110 =
11
#56
01
#57
1.
b0 ,
b0 :
b10111 (
b10111 =
11
#58
01
#59
b1 /
b1 7
b1 9
b11000 (
b11000 =
11
#60
01
#61
b0 ?
b1100 <
b11 ;
b11001 (
b11001 =
b10 /
b10 7
b10 9
11
#62
01
#63
b1000 <
0.
b11 /
b11 7
b11 9
1'
b1100 ,
b1100 :
11
#64
01
#65
0'
b1000 ,
b1000 :
b0 &
b0 2
b0 8
11
#66
01
#67
b1011 <
1%
11
#68
01
#69
1$
b1 ?
b11 <
1*
b1011 ,
b1011 :
0%
11
#70
01
#71
b0 ?
b1101 <
10
b111 ;
0*
b11 ,
b11 :
b11010 (
b11010 =
11
#72
01
#73
00
b1001 <
1#
b1101 ,
b1101 :
0+
b11111111 "
b11111111 3
b11111111 6
11
#74
01
#75
0#
b1001 ,
b1001 :
11
#76
01
#77
b1 ?
b111 <
1!
11
#78
01
#79
b11111111111111111111111111111110 ?
b1111 <
b0 ;
b111 ,
b111 :
b11011 (
b11011 =
0!
11
#80
01
#81
b11111111111111111111111111111111 ?
b11 ;
b1111 ,
b1111 :
b11001 (
b11001 =
11
#82
01
#83
b0 ;
b11000 (
b11000 =
11
#84
01
#85
b10111 (
b10111 =
11
#86
01
#87
b10110 (
b10110 =
11
#88
01
#89
b1 @
b111 ;
b10101 (
b10101 =
11
#90
01
#91
b0 @
b1 >
b10100 (
b10100 =
11
#92
b1 @
01
#93
b0 @
b10 >
b10011 (
b10011 =
11
#94
b1 @
01
#95
b0 @
b11 >
b1 ;
b10010 (
b10010 =
11
#96
01
#97
b10001 (
b10001 =
11
#98
01
#99
b10000 (
b10000 =
11
#100
01
#101
b11111111111111111111111111111111 @
b110 ;
b1111 (
b1111 =
11
#102
01
#103
b0 @
b10 >
b11 ;
b1110 (
b1110 =
11
#104
01
#105
b1 @
b111 ;
b1101 (
b1101 =
11
#106
01
#107
b0 @
b11 >
b0 ;
b1100 (
b1100 =
11
#108
01
#109
b11 ;
b1011 (
b1011 =
11
#110
01
#111
b1010 (
b1010 =
11
#112
01
#113
b1001 (
b1001 =
11
#114
01
#115
b11111111111111111111111111111111 @
b110 ;
b1000 (
b1000 =
11
#116
01
#117
b0 @
b10 >
b10 ;
b111 (
b111 =
11
#118
01
#119
b11111111111111111111111111111111 @
b110 ;
b110 (
b110 =
11
#120
01
#121
b0 @
b1 >
b1 ;
b101 (
b101 =
11
#122
01
#123
b100 (
b100 =
11
#124
01
#125
b11111111111111111111111111111111 @
b110 ;
b11 (
b11 =
11
#126
01
#127
b0 @
b0 >
b11 ;
b10 (
b10 =
11
#128
01
#129
b1010 <
b1 ?
b110 ;
b1 (
b1 =
11
#130
01
#131
b11 <
0$
b11 ;
b1010 ,
b1010 :
b10 (
b10 =
11
#132
01
#133
b0 ?
b1101 <
10
1$
b110 ;
b11 ,
b11 :
b11 (
b11 =
11
#134
01
#135
b1001 <
00
b11111110 "
b11111110 3
b11111110 6
1#
b1101 ,
b1101 :
11
#136
01
#137
0#
b1001 ,
b1001 :
11
#138
01
#139
b1 ?
b110 <
1!
11
#140
01
#141
0$
b1 <
b1 ;
b110 ,
b110 :
b100 (
b100 =
0!
11
#142
01
#143
1.
1$
b1 ,
b1 :
b101 (
b101 =
11
#144
01
#145
b0 ?
b1100 <
b110 ;
b110 (
b110 =
b10 /
b10 7
b10 9
11
#146
01
#147
b1000 <
0.
0$
b1 /
b1 7
b1 9
1'
b1100 ,
b1100 :
11
#148
01
#149
0'
b1000 ,
b1000 :
11
#150
01
#151
b1011 <
1%
11
#152
01
#153
1$
b1 ?
b110 <
1*
b1011 ,
b1011 :
0%
11
#154
01
#155
b0 ?
b1110 <
0$
1+
b0 "
b0 3
b0 6
b10 ;
0*
b110 ,
b110 :
b111 (
b111 =
11
#156
01
#157
b1 ?
b1110 ,
b1110 :
11
#158
01
#159
b1 @
b110 ;
b1000 (
b1000 =
11
#160
01
#161
b0 @
b1 >
b11 ;
b1001 (
b1001 =
11
#162
01
#163
b1010 (
b1010 =
11
#164
01
#165
b1011 (
b1011 =
11
#166
01
#167
b0 ;
b1100 (
b1100 =
11
#168
01
#169
b11111111111111111111111111111111 @
b111 ;
b1101 (
b1101 =
11
#170
01
#171
b0 @
b0 >
b11 ;
b1110 (
b1110 =
11
#172
01
#173
b1 @
b110 ;
b1111 (
b1111 =
11
#174
01
#175
b0 @
b1 >
b1 ;
b10000 (
b10000 =
11
#176
01
#177
b10001 (
b10001 =
11
#178
01
#179
b10010 (
b10010 =
11
#180
01
#181
b11111111111111111111111111111111 @
b111 ;
b10011 (
b10011 =
11
#182
01
#183
b0 @
b0 >
b10100 (
b10100 =
11
#184
b1010 <
01
#185
b111 <
b1010 ,
b1010 :
b10101 (
b10101 =
11
#186
01
#187
b0 <
1$
b0 ;
b111 ,
b111 :
b10110 (
b10110 =
11
#188
01
#189
1.
0$
b0 ,
b0 :
b10111 (
b10111 =
11
#190
01
#191
b10 /
b10 7
b10 9
b11000 (
b11000 =
11
#192
01
#193
b0 ?
b1100 <
b11 ;
b11001 (
b11001 =
b11 /
b11 7
b11 9
11
#194
01
#195
b1000 <
0.
b100 /
b100 7
b100 9
1'
b1100 ,
b1100 :
11
#196
01
#197
0'
b1000 ,
b1000 :
11
#198
01
#199
b1011 <
1%
11
#200
01
#201
1$
b1 ?
b11 <
1*
b1011 ,
b1011 :
0%
11
#202
01
#203
b0 ?
b1101 <
10
b111 ;
0*
b11 ,
b11 :
b11010 (
b11010 =
11
#204
01
#205
00
b1001 <
1#
b1101 ,
b1101 :
0+
b11111111 "
b11111111 3
b11111111 6
11
#206
01
#207
0#
b1001 ,
b1001 :
11
#208
01
#209
b1 ?
b111 <
1!
11
#210
01
#211
b11111111111111111111111111111110 ?
b1111 <
b0 ;
b111 ,
b111 :
b11011 (
b11011 =
0!
11
#212
01
#213
b11111111111111111111111111111111 ?
b11 ;
b1111 ,
b1111 :
b11001 (
b11001 =
11
#214
01
#215
b0 ;
b11000 (
b11000 =
11
#216
01
#217
b10111 (
b10111 =
11
#218
01
#219
b10110 (
b10110 =
11
#220
01
#221
b1 @
b111 ;
b10101 (
b10101 =
11
#222
01
#223
b0 @
b1 >
b10100 (
b10100 =
11
#224
b1 @
01
#225
b0 @
b10 >
b10011 (
b10011 =
11
#226
b1 @
01
#227
b0 @
b11 >
b1 ;
b10010 (
b10010 =
11
#228
01
#229
b10001 (
b10001 =
11
#230
01
#231
b10000 (
b10000 =
11
#232
01
#233
b11111111111111111111111111111111 @
b110 ;
b1111 (
b1111 =
11
#234
01
#235
b0 @
b10 >
b11 ;
b1110 (
b1110 =
11
#236
01
#237
b1 @
b111 ;
b1101 (
b1101 =
11
#238
01
#239
b0 @
b11 >
b0 ;
b1100 (
b1100 =
11
#240
01
#241
b11 ;
b1011 (
b1011 =
11
#242
01
#243
b1010 (
b1010 =
11
#244
01
#245
b1001 (
b1001 =
11
#246
01
#247
b11111111111111111111111111111111 @
b110 ;
b1000 (
b1000 =
11
#248
01
#249
b0 @
b10 >
b10 ;
b111 (
b111 =
11
#250
01
#251
b11111111111111111111111111111111 @
b110 ;
b110 (
b110 =
11
#252
01
#253
b0 @
b1 >
b1 ;
b101 (
b101 =
11
#254
01
#255
b100 (
b100 =
11
#256
01
#257
b11111111111111111111111111111111 @
b110 ;
b11 (
b11 =
11
#258
01
#259
b0 @
b0 >
b11 ;
b10 (
b10 =
11
#260
01
#261
b1010 <
b1 ?
b110 ;
b1 (
b1 =
11
#262
01
#263
b11 <
0$
b11 ;
b1010 ,
b1010 :
b10 (
b10 =
11
#264
01
#265
b0 ?
b1101 <
10
1$
b110 ;
b11 ,
b11 :
b11 (
b11 =
11
#266
01
#267
b1001 <
00
b11111110 "
b11111110 3
b11111110 6
1#
b1101 ,
b1101 :
11
#268
01
#269
0#
b1001 ,
b1001 :
11
#270
01
#271
b1 ?
b110 <
1!
11
#272
01
#273
0$
b1 <
b1 ;
b110 ,
b110 :
b100 (
b100 =
0!
11
#274
01
#275
1.
1$
b1 ,
b1 :
b101 (
b101 =
11
#276
01
#277
b0 ?
b1100 <
b110 ;
b110 (
b110 =
b11 /
b11 7
b11 9
11
#278
01
#279
b1000 <
0.
0$
b10 /
b10 7
b10 9
1'
b1100 ,
b1100 :
11
#280
01
#281
0'
b1000 ,
b1000 :
11
#282
01
#283
b1011 <
1%
11
#284
01
#285
1$
b1 ?
b110 <
1*
b1011 ,
b1011 :
0%
11
#286
01
#287
b0 ?
b1110 <
0$
1+
b0 "
b0 3
b0 6
b10 ;
0*
b110 ,
b110 :
b111 (
b111 =
11
#288
01
#289
b1 ?
b1110 ,
b1110 :
11
#290
01
#291
b1 @
b110 ;
b1000 (
b1000 =
11
#292
01
#293
b0 @
b1 >
b11 ;
b1001 (
b1001 =
11
#294
01
#295
b1010 (
b1010 =
11
#296
01
#297
b1011 (
b1011 =
11
#298
01
#299
b0 ;
b1100 (
b1100 =
11
#300
01
#301
b11111111111111111111111111111111 @
b111 ;
b1101 (
b1101 =
11
#302
01
#303
b0 @
b0 >
b11 ;
b1110 (
b1110 =
11
#304
01
#305
b1 @
b110 ;
b1111 (
b1111 =
11
#306
01
#307
b0 @
b1 >
b1 ;
b10000 (
b10000 =
11
#308
01
#309
b10001 (
b10001 =
11
#310
01
#311
b10010 (
b10010 =
11
#312
01
#313
b11111111111111111111111111111111 @
b111 ;
b10011 (
b10011 =
11
#314
01
#315
b0 @
b0 >
b10100 (
b10100 =
11
#316
b1010 <
01
#317
b111 <
b1010 ,
b1010 :
b10101 (
b10101 =
11
#318
01
#319
b0 <
1$
b0 ;
b111 ,
b111 :
b10110 (
b10110 =
11
#320
01
#321
1.
0$
b0 ,
b0 :
b10111 (
b10111 =
11
#322
01
#323
b11 /
b11 7
b11 9
b11000 (
b11000 =
11
#324
01
#325
b0 ?
b1100 <
b11 ;
b11001 (
b11001 =
b100 /
b100 7
b100 9
11
#326
01
#327
b1000 <
0.
b101 /
b101 7
b101 9
1'
b1100 ,
b1100 :
11
#328
01
#329
0'
b1000 ,
b1000 :
11
#330
01
#331
b1011 <
1%
11
#332
01
#333
1$
b1 ?
b11 <
1*
b1011 ,
b1011 :
0%
11
#334
01
#335
b0 ?
b1101 <
10
b111 ;
0*
b11 ,
b11 :
b11010 (
b11010 =
11
#336
01
#337
00
b1001 <
1#
b1101 ,
b1101 :
0+
b11111111 "
b11111111 3
b11111111 6
11
#338
01
#339
0#
b1001 ,
b1001 :
11
#340
01
#341
b1 ?
b111 <
1!
11
#342
01
#343
b11111111111111111111111111111110 ?
b1111 <
b0 ;
b111 ,
b111 :
b11011 (
b11011 =
0!
11
#344
01
#345
b11111111111111111111111111111111 ?
b11 ;
b1111 ,
b1111 :
b11001 (
b11001 =
11
#346
01
#347
b0 ;
b11000 (
b11000 =
11
#348
01
#349
b10111 (
b10111 =
11
#350
01
#351
b10110 (
b10110 =
11
#352
01
#353
b1 @
b111 ;
b10101 (
b10101 =
11
#354
01
#355
b0 @
b1 >
b10100 (
b10100 =
11
#356
b1 @
01
#357
b0 @
b10 >
b10011 (
b10011 =
11
#358
b1 @
01
#359
b0 @
b11 >
b1 ;
b10010 (
b10010 =
11
#360
01
#361
b10001 (
b10001 =
11
#362
01
#363
b10000 (
b10000 =
11
#364
01
#365
b11111111111111111111111111111111 @
b110 ;
b1111 (
b1111 =
11
#366
01
#367
b0 @
b10 >
b11 ;
b1110 (
b1110 =
11
#368
01
#369
b1 @
b111 ;
b1101 (
b1101 =
11
#370
01
#371
b0 @
b11 >
b0 ;
b1100 (
b1100 =
11
#372
01
#373
b11 ;
b1011 (
b1011 =
11
#374
01
#375
b1010 (
b1010 =
11
#376
01
#377
b1001 (
b1001 =
11
#378
01
#379
b11111111111111111111111111111111 @
b110 ;
b1000 (
b1000 =
11
#380
01
#381
b0 @
b10 >
b10 ;
b111 (
b111 =
11
#382
01
#383
b11111111111111111111111111111111 @
b110 ;
b110 (
b110 =
11
#384
01
#385
b0 @
b1 >
b1 ;
b101 (
b101 =
11
#386
01
#387
b100 (
b100 =
11
#388
01
#389
b11111111111111111111111111111111 @
b110 ;
b11 (
b11 =
11
#390
01
#391
b0 @
b0 >
b11 ;
b10 (
b10 =
11
#392
01
#393
b1010 <
b1 ?
b110 ;
b1 (
b1 =
11
#394
01
#395
b11 <
0$
b11 ;
b1010 ,
b1010 :
b10 (
b10 =
11
#396
01
#397
b0 ?
b1101 <
10
1$
b110 ;
b11 ,
b11 :
b11 (
b11 =
11
#398
01
#399
b1001 <
00
b11111110 "
b11111110 3
b11111110 6
1#
b1101 ,
b1101 :
11
#400
01
#401
0#
b1001 ,
b1001 :
11
#402
01
#403
b1 ?
b110 <
1!
11
#404
01
#405
0$
b1 <
b1 ;
b110 ,
b110 :
b100 (
b100 =
0!
11
#406
01
#407
1.
1$
b1 ,
b1 :
b101 (
b101 =
11
#408
01
#409
b0 ?
b1100 <
b110 ;
b110 (
b110 =
b100 /
b100 7
b100 9
11
#410
01
#411
b1000 <
0.
0$
b11 /
b11 7
b11 9
1'
b1100 ,
b1100 :
11
#412
01
#413
0'
b1000 ,
b1000 :
b11111110 &
b11111110 2
b11111110 8
11
#414
01
#415
b1011 <
1%
11
#416
01
#417
1$
b1 ?
b110 <
1*
b1011 ,
b1011 :
0%
11
#418
01
#419
b10 <
0$
b10 ;
0*
b110 ,
b110 :
b111 (
b111 =
11
#420
01
#421
b0 ?
b1101 <
10
b110 ;
b10 ,
b10 :
b1000 (
b1000 =
11
#422
01
#423
b1001 <
00
1$
b11111111 "
b11111111 3
b11111111 6
1#
b1101 ,
b1101 :
11
#424
01
#425
0#
b1001 ,
b1001 :
11
#426
01
#427
b1 ?
b110 <
1!
11
#428
01
#429
0$
b11 <
b11 ;
b110 ,
b110 :
b1001 (
b1001 =
0!
11
#430
01
#431
10
1$
b11 ,
b11 :
b1010 (
b1010 =
11
#432
01
#433
b1011 (
b1011 =
b11111110 "
b11111110 3
b11111110 6
11
#434
01
#435
b0 ?
b1101 <
b11111101 "
b11111101 3
b11111101 6
b0 ;
b1100 (
b1100 =
11
#436
01
#437
b1001 <
00
1#
b1101 ,
b1101 :
b11111100 "
b11111100 3
b11111100 6
11
#438
01
#439
0#
b1001 ,
b1001 :
11
#440
01
#441
b1 ?
b0 <
1!
11
#442
01
#443
1.
0$
b0 ?
b1100 <
b111 ;
b0 ,
b0 :
b1101 (
b1101 =
0!
11
#444
01
#445
b1000 <
0.
1'
b1100 ,
b1100 :
b100 /
b100 7
b100 9
11
#446
01
#447
0'
b1000 ,
b1000 :
11
#448
01
#449
b1011 <
1%
11
#450
01
#451
1$
b1 ?
b111 <
1*
b1011 ,
b1011 :
0%
11
#452
01
#453
b11111111111111111111111111111110 ?
b1111 <
b11 ;
0*
b111 ,
b111 :
b1110 (
b1110 =
b11111110 "
b11111110 3
b11111110 6
11
#454
01
#455
b11111111111111111111111111111111 ?
b0 ;
b1111 ,
b1111 :
b1100 (
b1100 =
11
#456
01
#457
b11 ;
b1011 (
b1011 =
11
#458
01
#459
b1010 (
b1010 =
11
#460
01
#461
b1001 (
b1001 =
11
#462
01
#463
b1010 <
b1 ?
b110 ;
b1000 (
b1000 =
11
#464
01
#465
b11 <
0$
b11 ;
b1010 ,
b1010 :
b1001 (
b1001 =
11
#466
01
#467
10
1$
b11 ,
b11 :
b1010 (
b1010 =
11
#468
01
#469
b1011 (
b1011 =
b11111101 "
b11111101 3
b11111101 6
11
#470
01
#471
b0 ?
b1101 <
b11111100 "
b11111100 3
b11111100 6
b0 ;
b1100 (
b1100 =
11
#472
01
